odoo/addons/server_environment_autocreate/LICENSE
odoo/addons/server_environment_autocreate/README.rst
odoo/addons/server_environment_autocreate/__init__.py
odoo/addons/server_environment_autocreate/__manifest__.py
odoo/addons/server_environment_autocreate/i18n/fr.po
odoo/addons/server_environment_autocreate/i18n/it.po
odoo/addons/server_environment_autocreate/i18n/server_environment_autocreate.pot
odoo/addons/server_environment_autocreate/models/__init__.py
odoo/addons/server_environment_autocreate/models/server_env_mixin.py
odoo/addons/server_environment_autocreate/readme/CONFIGURE.md
odoo/addons/server_environment_autocreate/readme/CONTEXT.md
odoo/addons/server_environment_autocreate/readme/CONTRIBUTORS.md
odoo/addons/server_environment_autocreate/readme/DESCRIPTION.md
odoo/addons/server_environment_autocreate/readme/ROADMAP.md
odoo/addons/server_environment_autocreate/readme/USAGE.md
odoo/addons/server_environment_autocreate/static/description/icon.png
odoo/addons/server_environment_autocreate/static/description/index.html
odoo/addons/server_environment_autocreate/tests/__init__.py
odoo/addons/server_environment_autocreate/tests/models.py
odoo/addons/server_environment_autocreate/tests/test_server_environment_autocreate.py
odoo/addons/server_environment_autocreate/tests/files/autocreate/base.conf
odoo/addons/server_environment_autocreate/tests/files/default/base.conf
odoo_addon_server_environment_autocreate-17.0.1.0.0.6.dist-info/METADATA
odoo_addon_server_environment_autocreate-17.0.1.0.0.6.dist-info/WHEEL
odoo_addon_server_environment_autocreate-17.0.1.0.0.6.dist-info/top_level.txt
odoo_addon_server_environment_autocreate-17.0.1.0.0.6.dist-info/RECORD
